livecaption/__init__.py
livecaption/config.py
livecaption/installer.py
livecaption/main.py
livecaption/native_host.py
livecaption/uninstaller.py
livecaption-1.0.1.dist-info/licenses/LICENSE
livecaption-1.0.1.dist-info/METADATA
livecaption-1.0.1.dist-info/WHEEL
livecaption-1.0.1.dist-info/entry_points.txt
livecaption-1.0.1.dist-info/top_level.txt
livecaption-1.0.1.dist-info/RECORD
