Metadata-Version: 2.4
Name: livecaption
Version: 1.0.1
Summary: Real-time audio transcription for video streaming with Firefox browser integration
Author: b-tok
License: MIT
Project-URL: Homepage, https://github.com/b-tok/LiveCaption
Project-URL: Issues, https://github.com/b-tok/LiveCaption/issues
Project-URL: Documentation, https://github.com/b-tok/LiveCaption#readme
Keywords: transcription,whisper,japanese,subtitles,firefox,streaming
Classifier: Development Status :: 4 - Beta
Classifier: Environment :: X11 Applications
Classifier: Intended Audience :: End Users/Desktop
Classifier: License :: OSI Approved :: MIT License
Classifier: Operating System :: POSIX :: Linux
Classifier: Programming Language :: Python :: 3
Classifier: Programming Language :: Python :: 3.9
Classifier: Programming Language :: Python :: 3.10
Classifier: Programming Language :: Python :: 3.11
Classifier: Topic :: Multimedia :: Sound/Audio :: Speech
Classifier: Topic :: Multimedia :: Video
Requires-Python: >=3.9
License-File: LICENSE
Requires-Dist: torch>=2.0.0
Requires-Dist: transformers>=4.36.0
Requires-Dist: accelerate>=0.25.0
Requires-Dist: sounddevice>=0.4.6
Requires-Dist: numpy>=1.24.0
Requires-Dist: silero-vad>=5.0.0
Provides-Extra: faster-whisper
Requires-Dist: faster-whisper>=0.10.0; extra == "faster-whisper"
Provides-Extra: dev
Requires-Dist: pytest>=7.0.0; extra == "dev"
Requires-Dist: black>=23.0.0; extra == "dev"
Requires-Dist: mypy>=1.0.0; extra == "dev"
Dynamic: license-file
Dynamic: requires-python
